{
  "placements": [
    {
      "x": 783.0,
      "y": 116.0
    },
    {
      "x": 841.0,
      "y": 131.0
    },
    {
      "x": 848.0,
      "y": 168.0
    },
    {
      "x": 842.0,
      "y": 117.0
    },
    {
      "x": 868.0,
      "y": 99.0
    },
    {
      "x": 787.0,
      "y": 146.0
    },
    {
      "x": 916.0,
      "y": 140.0
    },
    {
      "x": 880.0,
      "y": 123.0
    },
    {
      "x": 930.0,
      "y": 99.0
    },
    {
      "x": 789.0,
      "y": 91.0
    },
    {
      "x": 831.0,
      "y": 176.0
    },
    {
      "x": 782.0,
      "y": 132.0
    },
    {
      "x": 866.0,
      "y": 113.0
    }
  ]
}